chiapos.cpython-38-x86_64-linux-gnu.so
pos-0.0.0.dist-info/LICENSE
pos-0.0.0.dist-info/METADATA
pos-0.0.0.dist-info/WHEEL
pos-0.0.0.dist-info/top_level.txt
pos-0.0.0.dist-info/RECORD
