Metadata-Version: 2.1
Name: pos
Version: 0.0.0
Summary: Chia proof of space plotting, proving, and verifying (wraps C++)
Home-page: https://github.com/Chia-Network/chiavdf
Author: Mariano Sorgente
Author-email: mariano@chia.net
License: Apache License
Platform: UNKNOWN
Requires-Python: >=3.7
License-File: LICENSE
